dakada/Dakada.py
dakada/User.py
dakada/__init__.py
dakada/admin.py
dakada/blueprint.py
dakada/cookie.py
dakada/render.py
dakada/startproject.py
Dakada-2.1.dist-info/METADATA
Dakada-2.1.dist-info/WHEEL
Dakada-2.1.dist-info/top_level.txt
Dakada-2.1.dist-info/RECORD
