Metadata-Version: 2.1
Name: Dakada
Version: 2.1
Summary: A web framework by Dakada CN
Home-page: https://github.com/dakadayyds/dakadaWeb
Author: dakada
Author-email: s75uy1e@dingtalk.com
License: MIT
Classifier: License :: OSI Approved :: MIT License
Classifier: Programming Language :: Python
Classifier: Programming Language :: Python :: 3
Classifier: Programming Language :: Python :: 3.6
Classifier: Programming Language :: Python :: Implementation :: CPython
Classifier: Programming Language :: Python :: Implementation :: PyPy
Requires-Python: >=3.6.0
Requires-Dist: jinja2
